Metadata-Version: 2.1
Name: kinortho
Version: 1.0.0
Summary: KinOrtho v1.0.0
Home-page: https://github.com/esbgkannan/KinOrtho
Author: Liang-Chin Huang
Author-email: Leon1003@gmail.com
License: UNKNOWN
Platform: UNKNOWN
